ptvapi/__init__.py
ptvapi/api_client.py
ptvapi/configuration.py
ptvapi/rest.py
ptvapi/api/__init__.py
ptvapi/api/departures_api.py
ptvapi/api/directions_api.py
ptvapi/api/disruptions_api.py
ptvapi/api/outlets_api.py
ptvapi/api/patterns_api.py
ptvapi/api/route_types_api.py
ptvapi/api/routes_api.py
ptvapi/api/runs_api.py
ptvapi/api/search_api.py
ptvapi/api/signer.py
ptvapi/api/stops_api.py
ptvapi/models/__init__.py
ptvapi/models/v2_object.py
ptvapi/models/v3_bulk_departures_request.py
ptvapi/models/v3_bulk_departures_response.py
ptvapi/models/v3_bulk_departures_route_direction_response.py
ptvapi/models/v3_bulk_departures_stop_response.py
ptvapi/models/v3_bulk_departures_update_response.py
ptvapi/models/v3_departure.py
ptvapi/models/v3_departures_broad_parameters.py
ptvapi/models/v3_departures_response.py
ptvapi/models/v3_departures_specific_parameters.py
ptvapi/models/v3_direction.py
ptvapi/models/v3_direction_with_description.py
ptvapi/models/v3_directions_response.py
ptvapi/models/v3_disruption.py
ptvapi/models/v3_disruption_direction.py
ptvapi/models/v3_disruption_mode.py
ptvapi/models/v3_disruption_modes_response.py
ptvapi/models/v3_disruption_response.py
ptvapi/models/v3_disruption_route.py
ptvapi/models/v3_disruption_stop.py
ptvapi/models/v3_disruptions.py
ptvapi/models/v3_disruptions_response.py
ptvapi/models/v3_error_response.py
ptvapi/models/v3_outlet.py
ptvapi/models/v3_outlet_geolocation.py
ptvapi/models/v3_outlet_geolocation_parameters.py
ptvapi/models/v3_outlet_geolocation_response.py
ptvapi/models/v3_outlet_parameters.py
ptvapi/models/v3_outlet_response.py
ptvapi/models/v3_result_outlet.py
ptvapi/models/v3_result_route.py
ptvapi/models/v3_result_stop.py
ptvapi/models/v3_route.py
ptvapi/models/v3_route_departures_specific_parameters.py
ptvapi/models/v3_route_response.py
ptvapi/models/v3_route_service_status.py
ptvapi/models/v3_route_type.py
ptvapi/models/v3_route_types_response.py
ptvapi/models/v3_route_with_status.py
ptvapi/models/v3_run.py
ptvapi-1.0.0.dist-info/LICENSE
ptvapi-1.0.0.dist-info/METADATA
ptvapi-1.0.0.dist-info/WHEEL
ptvapi-1.0.0.dist-info/top_level.txt
ptvapi-1.0.0.dist-info/RECORD
