Metadata-Version: 2.1
Name: ptvapi
Version: 1.0.0
Summary: Python client for PTV Timetable API - Version 3
Home-page: https://rjk.xyz/ptvapi
Author: UNKNOWN
Author-email: richard.kendall@gmail.com
License: UNKNOWN
Keywords: PTV Timetable API,Australia,VIC,Victoria,Public,Transport
Platform: UNKNOWN
Requires-Dist: certifi (>=2017.4.17)
Requires-Dist: python-dateutil (>=2.1)
Requires-Dist: six (>=1.10)
Requires-Dist: urllib3 (>=1.23)
